django_sbomrepo-0.0.10.dist-info/licenses/LICENSE
sbomrepo/__init__.py
sbomrepo/apps.py
sbomrepo/models.py
sbomrepo/urls.py
sbomrepo/utils.py
sbomrepo/views.py
sbomrepo/management/__init__.py
sbomrepo/management/commands/__init__.py
sbomrepo/management/commands/resync_vulnerabilities.py
sbomrepo/migrations/0001_initial.py
sbomrepo/migrations/0002_alter_vulnerability_ecosystem.py
sbomrepo/migrations/__init__.py
django_sbomrepo-0.0.10.dist-info/METADATA
django_sbomrepo-0.0.10.dist-info/WHEEL
django_sbomrepo-0.0.10.dist-info/top_level.txt
django_sbomrepo-0.0.10.dist-info/RECORD
