Metadata-Version: 2.4
Name: django-sbomrepo
Version: 0.0.10
Summary: Software Bill of Materials Repository for Django
Author-email: InfoSec Engineering <surface@paddypowerbetfair.com>
License: MIT
Keywords: django,sbomrepo,sbom,dependencies,vulnerabilities,osv.dev,database
Classifier: Development Status :: 5 - Production/Stable
Classifier: Framework :: Django
Classifier: License :: OSI Approved :: MIT License
Classifier: Intended Audience :: Developers
Classifier: Operating System :: OS Independent
Classifier: Programming Language :: Python :: 3
Classifier: Environment :: Web Environment
Classifier: Topic :: Software Development
Requires-Python: >=3.7
License-File: LICENSE
Requires-Dist: Django<6.0,>=3.1
Requires-Dist: django-dynamicsettings>0.0.2
Requires-Dist: django-environ>0.5.0
Requires-Dist: requests<3,>2
Requires-Dist: tqdm<5
Requires-Dist: packageurl-python<1,>=0.15.1
Provides-Extra: dev
Requires-Dist: black==23.1.0; extra == "dev"
Requires-Dist: ruff==0.0.256; extra == "dev"
Provides-Extra: test
Requires-Dist: pytest==8.1.1; extra == "test"
Requires-Dist: pytest-django==4.8.0; extra == "test"
Requires-Dist: coverage==7.4.4; extra == "test"
Requires-Dist: responses==0.25.0; extra == "test"
Provides-Extra: prod
Requires-Dist: psycopg2-binary==2.9.9; extra == "prod"
Dynamic: license-file
